[
  {
    "id": "ORD-1001",
    "customer": "Alya Putri",
    "phone": "0812-3456-7890",
    "address": "Jl. Anggrek No. 12, Bandung",
    "channel": "Delivery",
    "status": "inquiry",
    "scheduled": "Hari ini 18:30",
    "total": 219000,
    "items": "Paket Parang x1",
    "notes": "Tanpa bawang",
    "orderCount": 0
  },
  {
    "id": "ORD-1002",
    "customer": "Bima Prasetyo",
    "phone": "0813-2200-4401",
    "address": "Komplek Setiabudi Residence Blok B2",
    "channel": "Delivery",
    "status": "confirmed",
    "scheduled": "Hari ini 19:00",
    "total": 119000,
    "items": "Paket Durang x1",
    "notes": "",
    "orderCount": 3
  },
  {
    "id": "ORD-1003",
    "customer": "Citra Lestari",
    "phone": "0815-9988-1122",
    "address": "Jl. Tamansari No. 55, Bandung",
    "channel": "Pickup",
    "status": "in_transit",
    "scheduled": "Hari ini 20:15",
    "total": 399000,
    "items": "Paket Serang x1",
    "notes": "Ulang tahun",
    "orderCount": 5
  },
  {
    "id": "ORD-1004",
    "customer": "Damar Hadi",
    "phone": "0812-9001-1144",
    "address": "Perumahan Melati, No. 8",
    "channel": "Delivery",
    "status": "delivered",
    "scheduled": "Kemarin 18:45",
    "total": 539000,
    "items": "Paket Balala x1",
    "notes": "",
    "orderCount": 8
  },
  {
    "id": "ORD-1005",
    "customer": "Eva Nuraini",
    "phone": "0811-2233-4455",
    "address": "Jl. Ciumbuleuit No. 17",
    "channel": "Pickup",
    "status": "returned",
    "scheduled": "Kemarin 20:30",
    "total": 119000,
    "items": "Paket Durang x1",
    "notes": "Kompor bermasalah",
    "orderCount": 1
  },
  {
    "id": "ORD-1006",
    "customer": "Fajar Santoso",
    "phone": "0817-4455-6677",
    "address": "Jl. Pajajaran No. 23",
    "channel": "Delivery",
    "status": "cancelled",
    "scheduled": "Hari ini 17:00",
    "total": 299000,
    "items": "Paket Jurang x1",
    "notes": "Cancel via WA",
    "orderCount": 2
  },
  {
    "id": "ORD-1007",
    "customer": "Gita Rahma",
    "phone": "0819-1100-2233",
    "address": "Jl. Sukajadi No. 90",
    "channel": "Delivery",
    "status": "confirmed",
    "scheduled": "Hari ini 21:00",
    "total": 219000,
    "items": "Paket Parang x1",
    "notes": "",
    "orderCount": 4
  },
  {
    "id": "ORD-1008",
    "customer": "Hadi Prabowo",
    "phone": "0812-3333-2211",
    "address": "Jl. Setiabudi No. 41",
    "channel": "Pickup",
    "status": "delivered",
    "scheduled": "Kemarin 19:10",
    "total": 299000,
    "items": "Paket Jurang x1",
    "notes": "",
    "orderCount": 6
  },
  {
    "id": "ORD-1009",
    "customer": "Intan Mahesa",
    "phone": "0813-5566-7788",
    "address": "Jl. Gegerkalong Hilir No. 3",
    "channel": "Delivery",
    "status": "in_transit",
    "scheduled": "Hari ini 19:40",
    "total": 399000,
    "items": "Paket Serang x1",
    "notes": "",
    "orderCount": 0
  },
  {
    "id": "ORD-1010",
    "customer": "Joko Prasetya",
    "phone": "0812-7777-8899",
    "address": "Jl. Pasteur No. 108",
    "channel": "Pickup",
    "status": "inquiry",
    "scheduled": "Hari ini 18:10",
    "total": 119000,
    "items": "Paket Durang x1",
    "notes": "",
    "orderCount": 0
  }
]
